[
  {
    "name": "Mark Davis",
    "company": "AEW",
    "imageURL": "https://static.wikia.nocookie.net/prowrestling/images/7/7b/Mark_Davis_Updated.png",
    "division": "Men's"
  },
  {
    "name": "Bryan Keith",
    "company": "AEW",
    "imageURL": "https://static.wikia.nocookie.net/prowrestling/images/2/2f/Bounty_Hunter_Bryan_Keith.jpg",
    "division": "Men's"
  },
  {
    "name": "Peter Avalon",
    "company": "AEW",
    "imageURL": "https://static.wikia.nocookie.net/prowrestling/images/e/ea/PeterAvalon2018.jpg",
    "division": "Men's"
  },
  {
    "name": "Madison Rayne",
    "company": "AEW",
    "imageURL": "https://static.wikia.nocookie.net/prowrestling/images/f/f8/Madison_Rayne_-_RoHbio.png",
    "division": "Women's"
  },
  {
    "name": "Griff Garrison",
    "company": "AEW",
    "imageURL": "https://static.wikia.nocookie.net/prowrestling/images/2/26/Griff_Garrison.png",
    "division": "Men's"
  },
  {
    "name": "Kenny Omega",
    "company": "AEW",
    "imageURL": "https://static.wikia.nocookie.net/puroresusystem/images/b/b2/KennyOmega5.jpg",
    "division": "Men's"
  },
  {
    "name": "Bryan Danielson",
    "company": "AEW",
    "imageURL": "https://static.wikia.nocookie.net/puroresusystem/images/2/29/BryanDanielson20241.jpg",
    "division": "Men's"
  },
  {
    "name": "Jon Moxley",
    "company": "AEW",
    "imageURL": "https://static.wikia.nocookie.net/puroresusystem/images/2/21/JonMoxley2024.jpg",
    "division": "Men's"
  },
  {
    "name": "Adam Page",
    "company": "AEW",
    "imageURL": "https://static.wikia.nocookie.net/prowrestling/images/f/fa/Hangman_Adam.PNG",
    "division": "Men's"
  },
  {
    "name": "Swerve Strickland",
    "company": "AEW",
    "imageURL": "https://static.wikia.nocookie.net/prowrestling/images/4/4c/Isaiah_Swerve_Scott_stat.png",
    "division": "Men's"
  },
  {
    "name": "Kota Ibushi",
    "company": "AEW",
    "imageURL": "https://static.wikia.nocookie.net/puroresusystem/images/c/c9/KotaIbushi2.jpg",
    "division": "Men's"
  },
  {
    "name": "Mercedes Moné",
    "company": "AEW",
    "imageURL": "https://static.wikia.nocookie.net/puroresusystem/images/9/96/MercedesMone.jpg",
    "division": "Women's"
  },
  {
    "name": "Jamie Hayter",
    "company": "AEW",
    "imageURL": "https://static.wikia.nocookie.net/prowrestling/images/8/83/Jamie_Hayter_2024.png",
    "division": "Women's"
  },
  {
    "name": "Kazuchika Okada",
    "company": "AEW",
    "imageURL": "https://static.wikia.nocookie.net/prowrestling/images/c/c2/Kazuchika_Okada_RainMaker.png",
    "division": "Men's"
  },
  {
    "name": "Willow Nightingale",
    "company": "AEW",
    "imageURL": "https://static.wikia.nocookie.net/puroresusystem/images/2/27/WillowNightingale.jpg",
    "division": "Women's"
  },
  {
    "name": "Hikaru Shida",
    "company": "AEW",
    "imageURL": "https://static.wikia.nocookie.net/prowrestling/images/f/f3/Hikaru_Shida_2023.png",
    "division": "Women's"
  },
  {
    "name": "MJF",
    "company": "AEW",
    "imageURL": "https://static.wikia.nocookie.net/theefed/images/a/a3/Mjf.jpg",
    "division": "Men's"
  },
  {
    "name": "Athena",
    "company": "AEW",
    "imageURL": "https://static.wikia.nocookie.net/prowrestling/images/b/b1/Ember_Moon.png",
    "division": "Women's"
  },
  {
    "name": "Ricochet",
    "company": "AEW",
    "imageURL": "https://static.wikia.nocookie.net/prowrestling/images/1/12/Ricochet_stat_photo.png",
    "division": "Men's"
  },
  {
    "name": "Will Ospreay",
    "company": "AEW",
    "imageURL": "https://static.wikia.nocookie.net/prowrestling/images/0/0d/Will_Ospreay_2022.png",
    "division": "Men's"
  },
  {
    "name": "Adam Cole",
    "company": "AEW",
    "imageURL": "https://static.wikia.nocookie.net/prowrestling/images/e/eb/Adam_Cole_stat_photo_2019.png",
    "division": "Men's"
  },
  {
    "name": "Claudio Castagnoli",
    "company": "AEW",
    "imageURL": "https://static.wikia.nocookie.net/prowrestling/images/e/e5/Cesaro_stat_photo.png",
    "division": "Men's"
  },
  {
    "name": "Eddie Kingston",
    "company": "AEW",
    "imageURL": "https://static.wikia.nocookie.net/prowrestling/images/a/a4/Eddie_Kingston_-_24176825.jpg",
    "division": "Men's"
  },
  {
    "name": "Jay White",
    "company": "AEW",
    "imageURL": "https://static.wikia.nocookie.net/prowrestling/images/0/08/Jay_White_2020.png",
    "division": "Men's"
  },
  {
    "name": "Toni Storm",
    "company": "AEW",
    "imageURL": "https://static.wikia.nocookie.net/prowrestling/images/a/a5/Timeless_Toni_Storm.png",
    "division": "Women's"
  },
  {
    "name": "Pac",
    "company": "AEW",
    "imageURL": "https://static.wikia.nocookie.net/prowrestling/images/7/75/Neville_%282017%29.png",
    "division": "Men's"
  },
  {
    "name": "Darby Allin",
    "company": "AEW",
    "imageURL": "https://static.wikia.nocookie.net/prowrestling/images/e/e3/Darby_Allin.png",
    "division": "Men's"
  },
  {
    "name": "Konosuke Takeshita",
    "company": "AEW",
    "imageURL": "https://static.wikia.nocookie.net/prowrestling/images/0/02/Konosuke_Takeshita_DDT_render.png",
    "division": "Men's"
  },
  {
    "name": "Kyle Fletcher",
    "company": "AEW",
    "imageURL": "https://static.wikia.nocookie.net/prowrestling/images/b/bf/Kyle_Fletcher_Shaved_Head.png",
    "division": "Men's"
  },
  {
    "name": "Samoa Joe",
    "company": "AEW",
    "imageURL": "https://static.wikia.nocookie.net/prowrestling/images/c/c9/Samoa_Joe_06_2015.png",
    "division": "Men's"
  },
  {
    "name": "Christian Cage",
    "company": "AEW",
    "imageURL": "https://static.wikia.nocookie.net/prowrestling/images/2/2a/Christian_full.png",
    "division": "Men's"
  },
  {
    "name": "Anthony Bowens",
    "company": "AEW",
    "imageURL": "https://static.wikia.nocookie.net/prowrestling/images/f/f8/Anthony_Bowens_-_D6EmE9zX4AQuVOZ.jpg",
    "division": "Men's"
  },
  {
    "name": "Chris Jericho",
    "company": "AEW",
    "imageURL": "https://static.wikia.nocookie.net/prowrestling/images/1/11/Chris_Jericho_-_2020.png",
    "division": "Men's"
  },
  {
    "name": "Cope",
    "company": "AEW",
    "imageURL": "https://static.wikia.nocookie.net/prowrestling/images/e/e6/EDGE_2022.png",
    "division": "Men's"
  },
  {
    "name": "Daniel Garcia",
    "company": "AEW",
    "imageURL": "https://static.wikia.nocookie.net/prowrestling/images/e/ea/Daniel_Garcia.jpg",
    "division": "Men's"
  },
  {
    "name": "Katsuyori Shibata",
    "company": "AEW",
    "imageURL": "https://static.wikia.nocookie.net/prowrestling/images/1/13/Katsuyori_Shibata_-_1d373298.jpg",
    "division": "Men's"
  },
  {
    "name": "Kris Statlander",
    "company": "AEW",
    "imageURL": "https://static.wikia.nocookie.net/prowrestling/images/5/55/Kris_Statlander_2023.png",
    "division": "Women's"
  },
  {
    "name": "Powerhouse Hobbs",
    "company": "AEW",
    "imageURL": "https://static.wikia.nocookie.net/prowrestling/images/2/2d/POWERHOUSE_HOBBS_-_NO_BG.png",
    "division": "Men's"
  },
  {
    "name": "Thekla",
    "company": "AEW",
    "imageURL": "https://static.wikia.nocookie.net/prowrestling/images/7/7b/Thekla_2025.png",
    "division": "Women's"
  },
  {
    "name": "Thunder Rosa",
    "company": "AEW",
    "imageURL": "https://static.wikia.nocookie.net/prowrestling/images/c/ce/Thunder_Rosa_2021_AEW.png",
    "division": "Women's"
  },
  {
    "name": "Anna Jay",
    "company": "AEW",
    "imageURL": "https://static.wikia.nocookie.net/prowrestling/images/0/06/Anna_Jay_A.S..png",
    "division": "Women's"
  },
  {
    "name": "Billie Starkz",
    "company": "AEW",
    "imageURL": "https://static.wikia.nocookie.net/prowrestling/images/8/84/Billie_Starkz_2024_2.png",
    "division": "Women's"
  },
  {
    "name": "Billy Gunn",
    "company": "AEW",
    "imageURL": "https://static.wikia.nocookie.net/prowrestling/images/a/aa/Billy_Gunn_%28Daddy_Ass%29_AEW_2023.png",
    "division": "Men's"
  },
  {
    "name": "Buddy Matthews",
    "company": "AEW",
    "imageURL": "https://static.wikia.nocookie.net/prowrestling/images/6/61/Buddy_Murphy_2018_stat_photo.png",
    "division": "Men's"
  },
  {
    "name": "Dante Martin",
    "company": "AEW",
    "imageURL": "https://static.wikia.nocookie.net/prowrestling/images/7/71/Daunte_Martin.jpg",
    "division": "Men's"
  },
  {
    "name": "Darius Martin",
    "company": "AEW",
    "imageURL": "https://static.wikia.nocookie.net/prowrestling/images/3/30/Darius_Martin_-_120802674.jpg",
    "division": "Men's"
  },
  {
    "name": "Dax Harwood",
    "company": "AEW",
    "imageURL": "https://static.wikia.nocookie.net/prowrestling/images/b/b3/Scott_Dawson.png",
    "division": "Men's"
  },
  {
    "name": "Jay Lethal",
    "company": "AEW",
    "imageURL": "https://static.wikia.nocookie.net/prowrestling/images/0/0d/Jay_Lethal_2016.png",
    "division": "Men's"
  },
  {
    "name": "Keith Lee",
    "company": "AEW",
    "imageURL": "https://static.wikia.nocookie.net/prowrestling/images/d/dc/Keith_Lee_stat_photo1.png",
    "division": "Men's"
  },
  {
    "name": "Lance Archer",
    "company": "AEW",
    "imageURL": "https://static.wikia.nocookie.net/prowrestling/images/8/87/Lance_Archer_2022.png",
    "division": "Men's"
  },
  {
    "name": "Mason Madden",
    "company": "AEW",
    "imageURL": "https://static.wikia.nocookie.net/prowrestling/images/d/d0/Mace2022.jpg",
    "division": "Men's"
  },
  {
    "name": "Max Caster",
    "company": "AEW",
    "imageURL": "https://static.wikia.nocookie.net/prowrestling/images/9/9e/Max_Caster_AEW1.jpg",
    "division": "Men's"
  },
  {
    "name": "Mansoor",
    "company": "AEW",
    "imageURL": "https://static.wikia.nocookie.net/prowrestling/images/8/81/Mansoor2022.jpg",
    "division": "Men's"
  },
  {
    "name": "Penelope Ford",
    "company": "AEW",
    "imageURL": "https://static.wikia.nocookie.net/prowrestling/images/5/51/Penelope_Ford_-_AEW_%27_19_Photo.jpg",
    "division": "Women's"
  },
  {
    "name": "Shelton Benjamin",
    "company": "AEW",
    "imageURL": "https://static.wikia.nocookie.net/prowrestling/images/4/45/Shelton_Benjamin_stat_photo.png",
    "division": "Men's"
  },
  {
    "name": "Skye Blue",
    "company": "AEW",
    "imageURL": "https://static.wikia.nocookie.net/prowrestling/images/f/fa/Skye_Blue_Dark_Look_AEW_2023.png",
    "division": "Women's"
  },
  {
    "name": "The Beast Mortos",
    "company": "AEW",
    "imageURL": "https://static.wikia.nocookie.net/prowrestling/images/8/8a/BlackTauro_B.jpg",
    "division": "Men's"
  },
  {
    "name": "Wheeler Yuta",
    "company": "AEW",
    "imageURL": "https://static.wikia.nocookie.net/prowrestling/images/5/53/Jimmy_Yuta_-_DDXgRp0UAAAiGM3.jpg",
    "division": "Men's"
  },
  {
    "name": "Marina Shafir",
    "company": "AEW",
    "imageURL": "https://static.wikia.nocookie.net/prowrestling/images/4/42/Marina_Shafir_2025.png",
    "division": "Women's"
  },
  {
    "name": "Action Andretti",
    "company": "AEW",
    "imageURL": "https://static.wikia.nocookie.net/prowrestling/images/d/d5/Action_Andretti.jpg",
    "division": "Men's"
  },
  {
    "name": "Mark Briscoe",
    "company": "AEW",
    "imageURL": "https://static.wikia.nocookie.net/prowrestling/images/6/68/Markbriscoebio_0.png",
    "division": "Men's"
  },
  {
    "name": "Wardlow",
    "company": "AEW",
    "imageURL": "https://static.wikia.nocookie.net/prowrestling/images/9/9a/Wardlow_-_EeXIhbFXsAAeDcO.jpg",
    "division": "Men's"
  },
  {
    "name": "Ruby Soho",
    "company": "AEW",
    "imageURL": "https://static.wikia.nocookie.net/prowrestling/images/e/e7/Ruby_Soho_AEW_Outcasts_Look_2023.png",
    "division": "Women's"
  },
  {
    "name": "Dr. Britt Baker, D.M.D.",
    "company": "AEW",
    "imageURL": "https://static.wikia.nocookie.net/prowrestling/images/0/08/Britt_Baker_2022_render.png",
    "division": "Women's"
  },
  {
    "name": "Nick Jackson",
    "company": "AEW",
    "imageURL": "https://static.wikia.nocookie.net/prowrestling/images/5/55/Nick_Jackson_AEW_2022.png",
    "division": "Men's"
  },
  {
    "name": "Jack Perry",
    "company": "AEW",
    "imageURL": "https://static.wikia.nocookie.net/prowrestling/images/8/8b/Jungle_Boy_2021.jpg",
    "division": "Men's"
  },
  {
    "name": "Lio Rush",
    "company": "AEW",
    "imageURL": "https://static.wikia.nocookie.net/prowrestling/images/6/69/Lio_Rush_stat_photo.png",
    "division": "Men's"
  },
  {
    "name": "Tay Melo",
    "company": "AEW",
    "imageURL": "https://static.wikia.nocookie.net/prowrestling/images/b/bd/Tay_Melo.png",
    "division": "Women's"
  },
  {
    "name": "Big Bill",
    "company": "AEW",
    "imageURL": "https://static.wikia.nocookie.net/prowrestling/images/b/b4/Big_Cass_-_2016.png",
    "division": "Men's"
  },
  {
    "name": "Colt Cabana",
    "company": "AEW",
    "imageURL": "https://static.wikia.nocookie.net/prowrestling/images/b/b1/1033_Colt_Cabana.png",
    "division": "Men's"
  },
  {
    "name": "The Blade",
    "company": "AEW",
    "imageURL": "https://static.wikia.nocookie.net/prowrestling/images/7/78/The_Blade_-_ELgthvqXsAA9XV2.jpg",
    "division": "Men's"
  },
  {
    "name": "Emi Sakura",
    "company": "AEW",
    "imageURL": "https://static.wikia.nocookie.net/prowrestling/images/a/a5/Emi_Sakura.jpg",
    "division": "Women's"
  },
  {
    "name": "Mike Bennett",
    "company": "AEW",
    "imageURL": "https://static.wikia.nocookie.net/prowrestling/images/1/18/Mike_Kanellis_stat--1647fcc1919fb4acd0a983613581da11.png",
    "division": "Men's"
  },
  {
    "name": "Red Velvet",
    "company": "AEW",
    "imageURL": "https://static.wikia.nocookie.net/prowrestling/images/2/2a/Red_Velvett_-_ProfPic_-_de2dl0h7df1f1c98b414649836f881460cf2a2d.png",
    "division": "Women's"
  },
  {
    "name": "Kamille",
    "company": "AEW",
    "imageURL": "https://static.wikia.nocookie.net/prowrestling/images/4/49/Kamille_-_169842758.jpg",
    "division": "Women's"
  },
  {
    "name": "Harley Cameron",
    "company": "AEW",
    "imageURL": "https://static.wikia.nocookie.net/prowrestling/images/8/8b/Harley_Cameron_2025.png",
    "division": "Women's"
  },
  {
    "name": "Killswitch",
    "company": "AEW",
    "imageURL": "https://static.wikia.nocookie.net/prowrestling/images/d/db/Luchasaurus_-_981-9813616.jpg",
    "division": "Men's"
  },
  {
    "name": "Colten Gunn",
    "company": "AEW",
    "imageURL": "https://static.wikia.nocookie.net/wrestlepedia/images/4/49/Colten_Gunn_03.jpg",
    "division": "Men's"
  },
  {
    "name": "Matt Sydal",
    "company": "AEW",
    "imageURL": "https://static.wikia.nocookie.net/puroresusystem/images/1/17/MattSydal.jpg",
    "division": "Men's"
  },
  {
    "name": "Leila Grey",
    "company": "AEW",
    "imageURL": "https://static.wikia.nocookie.net/prowrestling/images/d/d0/Leila_Grey_2023.png",
    "division": "Women's"
  },
  {
    "name": "Alex Windsor",
    "company": "AEW",
    "imageURL": "https://static.wikia.nocookie.net/prowrestling/images/a/a2/Alex_Windsor_2024.png",
    "division": "Women's"
  },
  {
    "name": "Nick Wayne",
    "company": "AEW",
    "imageURL": "https://static.wikia.nocookie.net/prowrestling/images/e/e2/Nick_Wayne1.jpg",
    "division": "Men's"
  },
  {
    "name": "Hologram",
    "company": "AEW",
    "imageURL": "https://static.wikia.nocookie.net/prowrestling/images/2/2e/Aramis_%28luchador%29.png",
    "division": "Men's"
  },
  {
    "name": "Matt Menard",
    "company": "AEW",
    "imageURL": "https://static.wikia.nocookie.net/wrestlepedia/images/b/bf/Matt_Menard_02.png",
    "division": "Men's"
  }
]